pars/__init__.py
pars/family_architectures.py
pars/hammer_to_object.py
pars/hmm_autosearch.py
pars/hmm_download.py
pars/hmmer_command.py
pars/hmmer_file.py
pars/pfam_architecture.py
pars/pfam_clan.py
pars/pfam_family.py
pars/pfam_sequences.py
pars/rfam_clan.py
pars/rfam_family.py
pars/rfamily_seq.py
pars/test.py
pars/xfam_object.py
pars/xfam_to.py
PARS-0.1.4.dist-info/LICENSE
PARS-0.1.4.dist-info/METADATA
PARS-0.1.4.dist-info/WHEEL
PARS-0.1.4.dist-info/entry_points.txt
PARS-0.1.4.dist-info/top_level.txt
PARS-0.1.4.dist-info/RECORD
