Metadata-Version: 2.1
Name: PARS
Version: 0.1.4
Summary: Project which enable automatic downloading data from pfam and rfam databases
Home-page: https://github.com/JuliaGol/PARS
Author: Julia Gołębiowska, Adam Cicherski, Patrycja Owczarek
Author-email: je.golebiowska@student.uw.edu.pl
License: MIT license
Project-URL: Bug Tracker, https://github.com/JuliaGol/PARS/issues
Keywords: PARS
Platform: UNKNOWN
Classifier: Development Status :: 2 - Pre-Alpha
Classifier: Intended Audience :: Developers
Classifier: License :: OSI Approved :: MIT License
Classifier: Natural Language :: English
Classifier: Programming Language :: Python :: 3
Classifier: Programming Language :: Python :: 3.6
Classifier: Programming Language :: Python :: 3.7
Classifier: Programming Language :: Python :: 3.8
Requires-Python: >=3.6
License-File: LICENSE
